MANIFEST.in
README.md
setup.cfg
setup.py
pydocker/Dockerfile.agent
pydocker/__init__.py
pydocker/cli.py
pydocker/entry.sh
pydocker/ssh.py
pydocker/status.py
pydocker/utils.py
pydocker/static/dashboard.css
pydocker/templates/index.html
sq_pydocker.egg-info/PKG-INFO
sq_pydocker.egg-info/SOURCES.txt
sq_pydocker.egg-info/dependency_links.txt
sq_pydocker.egg-info/entry_points.txt
sq_pydocker.egg-info/not-zip-safe
sq_pydocker.egg-info/requires.txt
sq_pydocker.egg-info/top_level.txt