Metadata-Version: 2.1
Name: sq-pydocker
Version: 0.3.2
Summary: Python package to make it easier to manage docker containers
Home-page: UNKNOWN
Author: Damien Ramunno-Johnson
Author-email: damien@squareup.com
License: UNKNOWN
Keywords: pydocker
Platform: UNKNOWN
Classifier: Intended Audience :: Developers
Classifier: Natural Language :: English
Classifier: Programming Language :: Python :: 2
Classifier: Programming Language :: Python :: 3
Provides-Extra: test
Provides-Extra: doc
